fuckzk/__init__.py
fuckzk/fuckzk.py
fuckzk-0.0.6.dist-info/LICENSE
fuckzk-0.0.6.dist-info/METADATA
fuckzk-0.0.6.dist-info/WHEEL
fuckzk-0.0.6.dist-info/top_level.txt
fuckzk-0.0.6.dist-info/RECORD
