Metadata-Version: 2.1
Name: fuckzk
Version: 0.0.6
Summary: A small function to obtain the health reporting and submission information of Zhengzhou Institute of science and technology.
Home-page: https://wildboarg.github.io/
Author: WildboarG
Author-email: 959586@outlook.com
License: UNKNOWN
Platform: UNKNOWN
Classifier: Programming Language :: Python :: 3
Classifier: License :: OSI Approved :: MIT License
License-File: LICENSE
Requires-Dist: requests (>=2.27.1)
